README.rst
setup.cfg
setup.py
dserve/__init__.py
dserve/cli.py
dserve.egg-info/PKG-INFO
dserve.egg-info/SOURCES.txt
dserve.egg-info/dependency_links.txt
dserve.egg-info/entry_points.txt
dserve.egg-info/requires.txt
dserve.egg-info/top_level.txt