Metadata-Version: 1.1
Name: dserve
Version: 0.1.1
Summary: Tool to serve a dataset over HTTP
Home-page: https://github.com/JIC-CSB/dserve
Author: Tjelvar Olsson
Author-email: tjelvar.olsson@jic.ac.uk
License: MIT
Download-URL: https://github.com/JIC-CSB/dserve/tarball/0.1.1
Platform: UNKNOWN
